falliant/__init__.py
falliant/__main__.py
falliant/block.py
falliant/constants.py
falliant/game.py
falliant/renderer.py
falliant/ui.py
falliant/images/screenshot.png
falliant-1.0.2.dist-info/licenses/LICENSE
falliant-1.0.2.dist-info/METADATA
falliant-1.0.2.dist-info/WHEEL
falliant-1.0.2.dist-info/entry_points.txt
falliant-1.0.2.dist-info/top_level.txt
falliant-1.0.2.dist-info/RECORD
