Metadata-Version: 2.4
Name: falliant
Version: 1.0.2
Summary: A terminal-based block stacking game
Author-email: Henry Sowell <henry@homelab.engineering>
License-Expression: MIT
Project-URL: Homepage, https://github.com/veteranbv/falliant
Project-URL: Bug Tracker, https://github.com/veteranbv/falliant/issues
Classifier: Programming Language :: Python :: 3
Classifier: Operating System :: OS Independent
Classifier: Environment :: Console :: Curses
Classifier: Topic :: Games/Entertainment :: Puzzle Games
Requires-Python: >=3.6
License-File: LICENSE
Requires-Dist: windows-curses; platform_system == "Windows"
Dynamic: license-file
